async_savers/__init__.py
async_savers/async_savers.py
async_savers/async_savers_zmq.py
async_savers/utils.py
async_savers-0.3.0.dist-info/METADATA
async_savers-0.3.0.dist-info/WHEEL
async_savers-0.3.0.dist-info/top_level.txt
async_savers-0.3.0.dist-info/RECORD
